{
    "(latency: 100, download: 5242880, upload: 5242880)": {
        "ClassicLoadTester": {
            "60": 1421,
            "43200": 1423,
            "604800": 1429,
            "31622400": 1456
        },
        "CacheV2LoadTester": {
            "60": 1432,
            "43200": 1433,
            "604800": 67088,
            "31622400": 1431
        }
    },
    "(latency: 40, download: 5242880, upload: 5242880)": {
        "ClassicLoadTester": {
            "60": 1375,
            "43200": 1219,
            "604800": 1219,
            "31622400": 1219
        },
        "CacheV2LoadTester": {
            "60": 57545,
            "43200": 1248,
            "604800": 1246,
            "31622400": 1265
        }
    }
}